[
    {
        "key": "01",
        "image": "../assets/images/projects/Utah-DMV.png",
        "imageAlt": "utahDMV",
        "title": "Utah DMV",
        "description": "UX & UI redesign of the Utah DMV website.  With targeted goals of determining high-demand tasks and simplification of vehicle registration user-flow.",        
        "primaryButtonLink": "https://www.figma.com/proto/fuauyZnCo5mZfZ8BqrvY0F/Utah-DMV?node-id=79%3A1285&scaling=scale-down-width&page-id=0%3A1&starting-point-node-id=79%3A1285&show-proto-sidebar=1",
        "primaryButtonText": "View Prototype App",
        "secondaryButtonLink": "https://docs.google.com/presentation/d/1URK-RisNBPW-S64a-YAlwjEBMzWvRO4A/edit?usp=sharing&ouid=108086159208834352979&rtpof=true&sd=true",
        "secondaryButtonText": "View Design Process",
        "footerLink": "./01",
        "footerLinkText": "View Project Details"
        
    },
    {
        "key": "02",
        "image": "../assets/images/under_construction.jpg",
        "imageAlt": "project2",
        "title": "Project 2 Coming Soon",
        "description": "Project 2 Details coming soon",
        "repoLink": "",
        "repoLinkText": "",
        "deployLink": "",
        "deployLinkText": ""
    }
]